["{\"0\":10595,\"Id\":10595,\"1\":\"E01 The Boy in the Iceberg.mp4\",\"Name\":\"E01 The Boy in the Iceberg.mp4\"}","{\"0\":10596,\"Id\":10596,\"1\":\"E02 The Avatar Returns.mp4\",\"Name\":\"E02 The Avatar Returns.mp4\"}","{\"0\":10597,\"Id\":10597,\"1\":\"E03 The Southern Air Temple.mp4\",\"Name\":\"E03 The Southern Air Temple.mp4\"}","{\"0\":10598,\"Id\":10598,\"1\":\"E04 The Warriors of Kyoshi.mp4\",\"Name\":\"E04 The Warriors of Kyoshi.mp4\"}","{\"0\":10599,\"Id\":10599,\"1\":\"E05 The King of Omashu.mp4\",\"Name\":\"E05 The King of Omashu.mp4\"}","{\"0\":10600,\"Id\":10600,\"1\":\"E06 Imprisoned.mp4\",\"Name\":\"E06 Imprisoned.mp4\"}","{\"0\":10601,\"Id\":10601,\"1\":\"E07 Winter Solstice, Part 1; The Spirit World.mp4\",\"Name\":\"E07 Winter Solstice, Part 1; The Spirit World.mp4\"}","{\"0\":10602,\"Id\":10602,\"1\":\"E08 Winter Solstice, Part 2; Avatar Roku.mp4\",\"Name\":\"E08 Winter Solstice, Part 2; Avatar Roku.mp4\"}","{\"0\":10603,\"Id\":10603,\"1\":\"E09 The Waterbending Scroll.mp4\",\"Name\":\"E09 The Waterbending Scroll.mp4\"}","{\"0\":10604,\"Id\":10604,\"1\":\"E10 Jet.mp4\",\"Name\":\"E10 Jet.mp4\"}","{\"0\":10605,\"Id\":10605,\"1\":\"E11 The Great Divide.mp4\",\"Name\":\"E11 The Great Divide.mp4\"}","{\"0\":10606,\"Id\":10606,\"1\":\"E12 The Storm.mp4\",\"Name\":\"E12 The Storm.mp4\"}","{\"0\":10607,\"Id\":10607,\"1\":\"E13 The Blue Spirit.mp4\",\"Name\":\"E13 The Blue Spirit.mp4\"}","{\"0\":10608,\"Id\":10608,\"1\":\"E14 The Fortuneteller.mp4\",\"Name\":\"E14 The Fortuneteller.mp4\"}","{\"0\":10609,\"Id\":10609,\"1\":\"E15 Bato of the Water Tribe.mp4\",\"Name\":\"E15 Bato of the Water Tribe.mp4\"}","{\"0\":10610,\"Id\":10610,\"1\":\"E16 The Deserter.mp4\",\"Name\":\"E16 The Deserter.mp4\"}","{\"0\":10611,\"Id\":10611,\"1\":\"E17 The Northern Air Temple.mp4\",\"Name\":\"E17 The Northern Air Temple.mp4\"}","{\"0\":10612,\"Id\":10612,\"1\":\"E18 The Waterbending Master.mp4\",\"Name\":\"E18 The Waterbending Master.mp4\"}","{\"0\":10613,\"Id\":10613,\"1\":\"E19 The Siege of the North, Part 1.mp4\",\"Name\":\"E19 The Siege of the North, Part 1.mp4\"}","{\"0\":10614,\"Id\":10614,\"1\":\"E20 The Siege of the North, Part 2.mp4\",\"Name\":\"E20 The Siege of the North, Part 2.mp4\"}"]